odoo/addons/storage_backend_s3/README.rst
odoo/addons/storage_backend_s3/__init__.py
odoo/addons/storage_backend_s3/__manifest__.py
odoo/addons/storage_backend_s3/components/__init__.py
odoo/addons/storage_backend_s3/components/s3_adapter.py
odoo/addons/storage_backend_s3/i18n/storage_backend_s3.pot
odoo/addons/storage_backend_s3/models/__init__.py
odoo/addons/storage_backend_s3/models/storage_backend.py
odoo/addons/storage_backend_s3/readme/CONFIGURE.rst
odoo/addons/storage_backend_s3/readme/CONTRIBUTORS.rst
odoo/addons/storage_backend_s3/readme/DESCRIPTION.rst
odoo/addons/storage_backend_s3/readme/ROADMAP.rst
odoo/addons/storage_backend_s3/static/description/icon.png
odoo/addons/storage_backend_s3/static/description/index.html
odoo/addons/storage_backend_s3/tests/__init__.py
odoo/addons/storage_backend_s3/tests/test_amazon_s3.py
odoo/addons/storage_backend_s3/tests/cassettes/AmazonS3Case.test_setting_and_getting_data_from_dir.yaml
odoo/addons/storage_backend_s3/tests/cassettes/AmazonS3Case.test_setting_and_getting_data_from_root.yaml
odoo/addons/storage_backend_s3/views/backend_storage_view.xml
odoo14_addon_storage_backend_s3-14.0.2.1.0.dist-info/METADATA
odoo14_addon_storage_backend_s3-14.0.2.1.0.dist-info/WHEEL
odoo14_addon_storage_backend_s3-14.0.2.1.0.dist-info/top_level.txt
odoo14_addon_storage_backend_s3-14.0.2.1.0.dist-info/RECORD
